{"externals": {"thetvdb": 278520, "tvrage": null, "imdb": "tt3671754"}, "name": "Karde\u015f Pay\u0131", "type": "Scripted", "_links": {"self": {"href": "http://api.tvmaze.com/shows/18020"}, "previousepisode": {"href": "http://api.tvmaze.com/episodes/823933"}}, "image": {"original": "http://tvmazecdn.com/uploads/images/original_untouched/61/152655.jpg", "medium": "http://tvmazecdn.com/uploads/images/medium_portrait/61/152655.jpg"}, "url": "http://www.tvmaze.com/shows/18020/karde-pay", "schedule": {"days": ["Thursday"], "time": "22:00"}, "id": 18020, "updated": 1467050698, "summary": "<p>Karde\u015f Pay\u0131 is a Turkish TV sitcom produced by NTC Medya. The show is about two brothers (Ahmet Kural and Murat Cemcir) and a sister (Seda Bakan). The two brothers have a plumbing company and they are trying to invent something that would make the world a better place.</p>", "network": {"name": "Star TV", "country": {"name": "Turkey", "code": "TR", "timezone": "Europe/Istanbul"}, "id": 409}, "runtime": 90, "language": "Turkish", "premiered": "2014-02-13", "status": "Ended", "rating": {"average": 9}, "weight": 0, "webChannel": null, "genres": ["Drama", "Comedy", "Family"]}