{"externals": {"thetvdb": 159591, "tvrage": 25522, "imdb": "tt1474684"}, "name": "Luther", "type": "Scripted", "_links": {"self": {"href": "http://api.tvmaze.com/shows/670"}, "previousepisode": {"href": "http://api.tvmaze.com/episodes/486496"}}, "image": {"original": "http://tvmazecdn.com/uploads/images/original_untouched/5/14769.jpg", "medium": "http://tvmazecdn.com/uploads/images/medium_portrait/5/14769.jpg"}, "url": "http://www.tvmaze.com/shows/670/luther", "schedule": {"days": ["Thursday"], "time": "21:00"}, "id": 670, "updated": 1470866834, "summary": "<p>Crime drama series starring Idris Elba as Luther, a near-genius murder detective whose brilliant mind can't always save him from the dangerous violence of his passions</p>", "network": {"name": "BBC One", "country": {"name": "United Kingdom", "code": "GB", "timezone": "Europe/London"}, "id": 12}, "runtime": 60, "language": "English", "premiered": "2010-05-04", "status": "Ended", "rating": {"average": 9}, "weight": 1, "webChannel": null, "genres": ["Drama", "Crime", "Mystery"]}