{"externals": {"thetvdb": 298868, "tvrage": null, "imdb": "tt4742876"}, "name": "Pitchers", "type": "Scripted", "_links": {"self": {"href": "http://api.tvmaze.com/shows/7329"}, "previousepisode": {"href": "http://api.tvmaze.com/episodes/416134"}}, "image": {"original": "http://tvmazecdn.com/uploads/images/original_untouched/27/67766.jpg", "medium": "http://tvmazecdn.com/uploads/images/medium_portrait/27/67766.jpg"}, "url": "http://www.tvmaze.com/shows/7329/pitchers", "schedule": {"days": [], "time": ""}, "id": 7329, "updated": 1456389243, "summary": "<p>Four friends Naveen Bansal (Naveen), Jitendra Maheshwari (Jitu), Yogendra Kumar (Yogi) and Saurabh Mandal (Mandal), decide to enter the start-up world by launching their own start-up. Things are kicked off by Naveen who, angry at not being given his due at work, resigns in a drunk state. At the same time, he receives news of his B-Plan reaching the final round of the NASSCOM start-up conclave. This begins a series of situations in which the four friends rediscover what they really want in life and the challenges they face in getting their start-up idea off the ground.It's story is inspired from HBO TV series \"Silicon Valley\" but the plot is well designed in accordance with Indian audience who are not well aware of the Idea of Startup.</p>", "network": null, "runtime": 45, "language": "Hindi", "premiered": "2015-06-09", "status": "Running", "rating": {"average": 9}, "weight": 0, "webChannel": {"name": "YouTube", "country": {"name": "United States", "code": "US", "timezone": "America/New_York"}, "id": 21}, "genres": []}