[{"name": "The Proposal", "number": 1, "_links": {"self": {"href": "http://api.tvmaze.com/episodes/773319"}}, "season": 1, "url": "http://www.tvmaze.com/episodes/773319/permanent-roommates-1x01-the-proposal", "image": null, "id": 773319, "airstamp": "2014-10-29T12:00:00+00:00", "summary": "", "runtime": 21, "airdate": "2014-10-29", "airtime": ""}, {"name": "The Father (-In-Law)", "number": 2, "_links": {"self": {"href": "http://api.tvmaze.com/episodes/773320"}}, "season": 1, "url": "http://www.tvmaze.com/episodes/773320/permanent-roommates-1x02-the-father-in-law", "image": null, "id": 773320, "airstamp": "2014-11-05T12:00:00+00:00", "summary": "", "runtime": 21, "airdate": "2014-11-05", "airtime": ""}, {"name": "The Bachelor Pad", "number": 3, "_links": {"self": {"href": "http://api.tvmaze.com/episodes/773321"}}, "season": 1, "url": "http://www.tvmaze.com/episodes/773321/permanent-roommates-1x03-the-bachelor-pad", "image": null, "id": 773321, "airstamp": "2014-11-19T12:00:00+00:00", "summary": "", "runtime": 21, "airdate": "2014-11-19", "airtime": ""}, {"name": "The Bridegroom", "number": 4, "_links": {"self": {"href": "http://api.tvmaze.com/episodes/773322"}}, "season": 1, "url": "http://www.tvmaze.com/episodes/773322/permanent-roommates-1x04-the-bridegroom", "image": null, "id": 773322, "airstamp": "2014-11-26T12:00:00+00:00", "summary": "", "runtime": 21, "airdate": "2014-11-26", "airtime": ""}, {"name": "The Agreement", "number": 5, "_links": {"self": {"href": "http://api.tvmaze.com/episodes/773323"}}, "season": 1, "url": "http://www.tvmaze.com/episodes/773323/permanent-roommates-1x05-the-agreement", "image": null, "id": 773323, "airstamp": "2014-12-12T12:00:00+00:00", "summary": "", "runtime": 21, "airdate": "2014-12-12", "airtime": ""}, {"name": "The Parents", "number": 1, "_links": {"self": {"href": "http://api.tvmaze.com/episodes/773324"}}, "season": 2, "url": "http://www.tvmaze.com/episodes/773324/permanent-roommates-2x01-the-parents", "image": null, "id": 773324, "airstamp": "2016-02-14T12:00:00+00:00", "summary": "", "runtime": 21, "airdate": "2016-02-14", "airtime": ""}, {"name": "The Man", "number": 2, "_links": {"self": {"href": "http://api.tvmaze.com/episodes/773325"}}, "season": 2, "url": "http://www.tvmaze.com/episodes/773325/permanent-roommates-2x02-the-man", "image": null, "id": 773325, "airstamp": "2016-02-28T12:00:00+00:00", "summary": "", "runtime": 21, "airdate": "2016-02-28", "airtime": ""}, {"name": "The Event - Part I", "number": 3, "_links": {"self": {"href": "http://api.tvmaze.com/episodes/773326"}}, "season": 2, "url": "http://www.tvmaze.com/episodes/773326/permanent-roommates-2x03-the-event-part-i", "image": null, "id": 773326, "airstamp": "2016-03-13T12:00:00+00:00", "summary": "", "runtime": 21, "airdate": "2016-03-13", "airtime": ""}, {"name": "The Event - Part II", "number": 4, "_links": {"self": {"href": "http://api.tvmaze.com/episodes/773327"}}, "season": 2, "url": "http://www.tvmaze.com/episodes/773327/permanent-roommates-2x04-the-event-part-ii", "image": null, "id": 773327, "airstamp": "2016-03-25T12:00:00+00:00", "summary": "", "runtime": 21, "airdate": "2016-03-25", "airtime": ""}, {"name": "The Dinner", "number": 5, "_links": {"self": {"href": "http://api.tvmaze.com/episodes/773328"}}, "season": 2, "url": "http://www.tvmaze.com/episodes/773328/permanent-roommates-2x05-the-dinner", "image": null, "id": 773328, "airstamp": "2016-04-08T12:00:00+00:00", "summary": "", "runtime": 21, "airdate": "2016-04-08", "airtime": ""}, {"name": "The Memories", "number": 6, "_links": {"self": {"href": "http://api.tvmaze.com/episodes/829563"}}, "season": 2, "url": "http://www.tvmaze.com/episodes/829563/permanent-roommates-2x06-the-memories", "image": null, "id": 829563, "airstamp": "2016-05-22T12:00:00+00:00", "summary": "", "runtime": 21, "airdate": "2016-05-22", "airtime": ""}, {"name": "The Gift", "number": 7, "_links": {"self": {"href": "http://api.tvmaze.com/episodes/829562"}}, "season": 2, "url": "http://www.tvmaze.com/episodes/829562/permanent-roommates-2x07-the-gift", "image": null, "id": 829562, "airstamp": "2016-06-07T12:00:00+00:00", "summary": "", "runtime": 21, "airdate": "2016-06-07", "airtime": ""}, {"name": "The Attempt", "number": 8, "_links": {"self": {"href": "http://api.tvmaze.com/episodes/845778"}}, "season": 2, "url": "http://www.tvmaze.com/episodes/845778/permanent-roommates-2x08-the-attempt", "image": null, "id": 845778, "airstamp": "2016-06-24T12:00:00+00:00", "summary": "", "runtime": 21, "airdate": "2016-06-24", "airtime": ""}]